LICENSE
MANIFEST.in
README.md
setup.cfg
setup.py
script/bootstrap
script/build
script/release
tests/__init__.py
tests/api/__init__.py
tests/api/api_test_data.py
tests/api/test_file_upload.py
tests/api/test_login.py
tests/api/test_nanopub_crud.py
tests/api/test_sparql.py
tests/api/test_tableview.py
tests/api/view/__init__.py
tests/api/view/test_attributes_json_view.py
tests/api/view/test_describe_json_view.py
tests/api/view/test_describe_ontology_json_view.py
tests/api/view/test_entity_resolver_view.py
tests/api/view/test_labels_json_view.py
tests/api/view/test_latest_json_view.py
tests/api/view/test_nanopublications_json_view.py
tests/api/view/test_search_api_json_view.py
tests/api/view/test_summary_json_view.py
tests/integration/.gitignore
tests/integration/cypress.json
tests/integration/package.json
tests/integration/cypress/fixtures/credentials.json
tests/integration/cypress/fixtures/example.json
tests/integration/cypress/integration/examples/actions.spec.js
tests/integration/cypress/integration/examples/aliasing.spec.js
tests/integration/cypress/integration/examples/assertions.spec.js
tests/integration/cypress/integration/examples/connectors.spec.js
tests/integration/cypress/integration/examples/cookies.spec.js
tests/integration/cypress/integration/examples/cypress_api.spec.js
tests/integration/cypress/integration/examples/files.spec.js
tests/integration/cypress/integration/examples/local_storage.spec.js
tests/integration/cypress/integration/examples/location.spec.js
tests/integration/cypress/integration/examples/misc.spec.js
tests/integration/cypress/integration/examples/navigation.spec.js
tests/integration/cypress/integration/examples/network_requests.spec.js
tests/integration/cypress/integration/examples/querying.spec.js
tests/integration/cypress/integration/examples/spies_stubs_clocks.spec.js
tests/integration/cypress/integration/examples/traversal.spec.js
tests/integration/cypress/integration/examples/utilities.spec.js
whyis.egg-info/PKG-INFO
whyis.egg-info/SOURCES.txt
whyis.egg-info/dependency_links.txt
whyis.egg-info/entry_points.txt
whyis.egg-info/requires.txt
whyis.egg-info/top_level.txt
